odoo/addons/helpdesk_mgmt_activity/README.rst
odoo/addons/helpdesk_mgmt_activity/__init__.py
odoo/addons/helpdesk_mgmt_activity/__manifest__.py
odoo/addons/helpdesk_mgmt_activity/i18n/helpdesk_mgmt_activity.pot
odoo/addons/helpdesk_mgmt_activity/i18n/it.po
odoo/addons/helpdesk_mgmt_activity/models/__init__.py
odoo/addons/helpdesk_mgmt_activity/models/helpdesk_ticket.py
odoo/addons/helpdesk_mgmt_activity/models/helpdesk_ticket_team.py
odoo/addons/helpdesk_mgmt_activity/models/mail_activity.py
odoo/addons/helpdesk_mgmt_activity/models/res_config_settings.py
odoo/addons/helpdesk_mgmt_activity/readme/CONFIGURE.md
odoo/addons/helpdesk_mgmt_activity/readme/CONTEXT.md
odoo/addons/helpdesk_mgmt_activity/readme/CONTRIBUTORS.md
odoo/addons/helpdesk_mgmt_activity/readme/DESCRIPTION.md
odoo/addons/helpdesk_mgmt_activity/readme/USAGE.md
odoo/addons/helpdesk_mgmt_activity/static/description/icon.png
odoo/addons/helpdesk_mgmt_activity/static/description/index.html
odoo/addons/helpdesk_mgmt_activity/static/img/helpdesk_activity_fields.png
odoo/addons/helpdesk_mgmt_activity/static/img/settings.png
odoo/addons/helpdesk_mgmt_activity/static/img/team.png
odoo/addons/helpdesk_mgmt_activity/tests/__init__.py
odoo/addons/helpdesk_mgmt_activity/tests/test_helpdesk_ticket.py
odoo/addons/helpdesk_mgmt_activity/views/helpdesk_ticket_team_views.xml
odoo/addons/helpdesk_mgmt_activity/views/helpdesk_ticket_view.xml
odoo/addons/helpdesk_mgmt_activity/views/mail_activity_views.xml
odoo/addons/helpdesk_mgmt_activity/views/res_config_settings_views.xml
odoo_addon_helpdesk_mgmt_activity-18.0.1.0.0.2.dist-info/METADATA
odoo_addon_helpdesk_mgmt_activity-18.0.1.0.0.2.dist-info/WHEEL
odoo_addon_helpdesk_mgmt_activity-18.0.1.0.0.2.dist-info/top_level.txt
odoo_addon_helpdesk_mgmt_activity-18.0.1.0.0.2.dist-info/RECORD
