Metadata-Version: 2.1
Name: odoo-addon-helpdesk_mgmt_activity
Version: 18.0.1.0.0.2
Requires-Python: >=3.10
Requires-Dist: odoo-addon-helpdesk_mgmt==18.0.*
Requires-Dist: odoo==18.0.*
Summary: Create Activities for Odoo records from the Helpdesk
Home-page: https://github.com/OCA/helpdesk
License: AGPL-3
Author: =?utf-8?q?Cetmix_O=C3=9C=2C_Odoo_Community_Association_=28OCA=29?=
Author-email: support@odoo-community.org
Classifier: Programming Language :: Python
Classifier: Framework :: Odoo
Classifier: Framework :: Odoo :: 18.0
Classifier: License :: OSI Approved :: GNU Affero General Public License v3
